[
    {
        "name": "リーリア",
        "message": "「…………」"
    },
    {
        "name": "*S-event1_014_9_1",
        "message": "那个……是谁？"
    },
    {
        "name": "リーリア",
        "message": "「塞德娜长官」"
    },
    {
        "name": "リーリア",
        "message": "「………真是的，那个人为什么这么迟钝啊！」"
    },
    {
        "name": "リーリア",
        "message": "「明明是个好气氛，全被搞砸了啊！？」"
    },
    {
        "name": "リーリア",
        "message": "「嗯，这样无视她……好像也不行吧？　唉……」"
    },
    {
        "name": "リーリア",
        "message": "「是，长官，什么事？　呃……现在吗？　可以的，不过……」"
    },
    {
        "name": "リーリア",
        "message": "「……明白了，我也在外面，现在过去」"
    },
    {
        "name": "リーリア",
        "message": "「唉……虽然不知道怎么回事，但被叫过去了，我去一下」"
    },
    {
        "name": "セドナ",
        "message": "「来了啊」"
    },
    {
        "name": "リーリア",
        "message": "「是，来了，不过……突然有什么事吗？」"
    },
    {
        "name": "セドナ",
        "message": "「嗯……怎么了？　看起来心情不太好啊……」"
    },
    {
        "name": "リーリア",
        "message": "「没有那回事。完全没有！」"
    },
    {
        "name": "セドナ",
        "message": "「是吗……算了，没关系。坐下吧，放松点」"
    },
    {
        "name": "リーリア",
        "message": "「是，明白了……」"
    },
    {
        "name": "セドナ",
        "message": "「嗯……」"
    },
    {
        "name": "リーリア",
        "message": "「…………」"
    },
    {
        "name": "セドナ",
        "message": "「…………」"
    },
    {
        "name": "リーリア",
        "message": "「那个……长官？　所以，有什么事吗？」"
    },
    {
        "name": "セドナ",
        "message": "「……你，觉得我怎么样？」"
    },
    {
        "name": "リーリア",
        "message": "「啊？　……唉，怎么说呢……我的上司？」"
    },
    {
        "name": "セドナ",
        "message": "「不是那样的……」"
    },
    {
        "name": "リーリア",
        "message": "「怎么了？　今天很少见地吞吞吐吐的啊」"
    },
    {
        "name": "セドナ",
        "message": "「嗯……是啊……」"
    },
    {
        "name": "セドナ",
        "message": "「今天一天，看着你对新星星徒会的大家的态度，我有了一个感觉……」"
    },
    {
        "name": "リーリア",
        "message": "「是，是……」"
    },
    {
        "name": "セドナ",
        "message": "「看来我们俩是无法相容的存在啊」"
    },
    {
        "name": "リーリア",
        "message": "「……啊？」"
    },
    {
        "name": "セドナ",
        "message": "「我有我的信念，你也一定有你的信念。如果这样下去，我们永远无法交汇的两条线……」"
    },
    {
        "name": "リーリア",
        "message": "「啊，那个……所以，到底想说什么呢……？」"
    },
    {
        "name": "セドナ",
        "message": "「我想解决这个问题。想消除我们之间的隔阂」"
    },
    {
        "name": "セドナ",
        "message": "「所以，为了这个……那个…………嗯……」"
    },
    {
        "name": "リーリア",
        "message": "「……？」"
    },
    {
        "name": "セドナ",
        "message": "「我们来“谈谈”吧！！」"
    },
    {
        "name": "リーリア",
        "message": "「………………」"
    },
    {
        "name": "セドナ",
        "message": "「我无法接受你的想法，但可以理解！」"
    },
    {
        "name": "セドナ",
        "message": "「所以，我也不希望你按照我的想法来。只是希望你能听，能知道，能理解！」"
    },
    {
        "name": "セドナ",
        "message": "「为了这个，需要对话。所以莉莉娅，更多地和我——」"
    },
    {
        "name": "リーリア",
        "message": "「那个……」"
    },
    {
        "name": "セドナ",
        "message": "「嗯，什么？」"
    },
    {
        "name": "リーリア",
        "message": "「难道是为了这种事，才把我叫出来的吗？」"
    },
    {
        "name": "セドナ",
        "message": "「『这种事』可不是……！　这对我们来说是很重要的事情，进而对组织来说也是――！」"
    },
    {
        "name": "リーリア",
        "message": "「啊～～！　已经，不是那样的！　也～～～～、真是的！！」"
    },
    {
        "name": "リーリア",
        "message": "「长官是个认真的人，认真考虑各种事情，为了大家做出最好的选择――」"
    },
    {
        "name": "リーリア",
        "message": "「这种事情一个个解释给我听也没用，我都明白了！！」"
    },
    {
        "name": "セドナ",
        "message": "「是、是吗……」"
    },
    {
        "name": "リーリア",
        "message": "「还有，不擅长享受，读不懂气氛，但完全没有恶意！」"
    },
    {
        "name": "リーリア",
        "message": "「正因为如此才糟糕！　如果不是这样，事情会简单得多！」"
    },
    {
        "name": "リーリア",
        "message": "「已经不需要勉强打开心扉，或者反省了！　那样只会是浪费时间！」"
    },
    {
        "name": "セドナ",
        "message": "（嗯？　比我想象的更严重啊？）"
    },
    {
        "name": "リーリア",
        "message": "「话说，为什么那么破坏性地不懂得察言观色呢！？」"
    },
    {
        "name": "リーリア",
        "message": "「明明是个好时机！　明明是个非常好的时机！！」"
    },
    {
        "name": "リーリア",
        "message": "「虽然途中有点想，雏说『如果能维持现在的关系，或许就满足了』什么的！」"
    },
    {
        "name": "リーリア",
        "message": "「但即便如此！　既然气氛都出来了，当然想要继续下去啊！！」"
    },
    {
        "name": "セドナ",
        "message": "「莉莉娅，你在生什么气我都搞不清楚了？　好好按照顺序解释清楚」"
    },
    {
        "name": "リーリア",
        "message": "「解、解～～～！？　怎么可能解释得清楚！　真是个傻瓜！？」"
    },
    {
        "name": "セドナ",
        "message": "「真是幼稚的骂人话。这样什么都不明白，什么也开始不了吧！」"
    },
    {
        "name": "リーリア",
        "message": "「开始不了也没关系！　理解不了也没关系！」"
    },
    {
        "name": "リーリア",
        "message": "「只是在任性地生气而已，我的事情就放着不管吧！」"
    },
    {
        "name": "セドナ",
        "message": "「放着不管可不行！　你可是我的部下啊！」"
    },
    {
        "name": "リーリア",
        "message": "「那种话就是多管闲事！」"
    },
    {
        "name": "セドナ",
        "message": "「唔、唔……从刚才开始就不知道在说什么……连我也忍无可忍了……？」"
    },
    {
        "name": "リーリア",
        "message": "「什么啊！？　要打架吗？　好啊？　打就打吧！？」"
    },
    {
        "name": "セドナ",
        "message": "「好觉悟……全力以赴吧！！！」"
    },
    {
        "name": "リノ",
        "message": "「哎呀哎呀，好像变得很严重了？」"
    },
    {
        "name": "*S-event1_014_9_2",
        "message": "塞德娜有没有对你说了什么？"
    },
    {
        "name": "*S-event1_014_9_2",
        "message": "难道是妈妈……"
    },
    {
        "name": "リノ",
        "message": "「说吹了什么，听起来真难听。我只是轻轻地推了一下朋友的背而已呢♪」"
    },
    {
        "name": "マトイ",
        "message": "「那个，不阻止没关系吗？」"
    },
    {
        "name": "ヴィーナス",
        "message": "「没问题没问题！拳头与拳头相撞，互相理解。这才是青春的感觉吧？」"
    },
    {
        "name": "*S-event1_014_9_3",
        "message": "难道一直在看……？"
    },
    {
        "name": "*S-event1_014_9_3",
        "message": "哇，大家！？"
    },
    {
        "name": "サーシャ",
        "message": "「是的，其实从一开始就一直在看呢～」"
    },
    {
        "name": "アナ",
        "message": "「魔力式泳装的对决……这真是让人无法移开目光」"
    },
    {
        "name": "アイリーン",
        "message": "「希望雨过天晴吧～」"
    },
    {
        "name": "リーリア",
        "message": "「比赛开始了！哇哦哦哦哦哦哦！！！」"
    },
    {
        "name": "セドナ",
        "message": "「比赛开始了！哦哦哦哦哦哦！！！！」"
    },
    {
        "message": "莉莉娅和塞德娜的魔法相撞的声音，像是宣布战斗开始的钟声一样响彻云霄。"
    }
]