[
    {
        "name": "Title",
        "message": "第3话,赛西娅的妈妈理论,P"
    },
    {
        "message": "某一天在星徒会室。莎夏正在对来玩的赛西娅发动攻势。"
    },
    {
        "name": "サーシャ",
        "message": "「小赛西娅～一次就好，你也叫我一声妈妈嘛～！」"
    },
    {
        "name": "サーシャ",
        "message": "「你看，姐姐我很擅长裁缝，今天就用蕾丝给你做了很多你最喜欢的蝴蝶哦～？」"
    },
    {
        "name": "セシア",
        "message": "「盯～……」"
    },
    {
        "name": "サーシャ",
        "message": "「怎么样？ 这样一来在妈妈这边就加一分――」"
    },
    {
        "name": "セシア",
        "message": "「虽然我觉得你做的蝴蝶非常棒，但莎夏果然还是不能当我妈妈呢」"
    },
    {
        "name": "サーシャ",
        "message": "「怎么这样～！」"
    },
    {
        "name": "*S-1069001_a_3_1",
        "message": "莎夏今天也失败了啊……"
    },
    {
        "message": "我刚想说“我觉得莎夏在星徒会里也是最有母性的人了”，――"
    },
    {
        "name": "セシア",
        "message": "「会长，母性与年龄和性别无关哦。圣诞节的时候我也说过了，重要的是有没有能让人撒娇的妈味儿哦」"
    },
    {
        "name": "セシア",
        "message": "「我确实能感觉到，莎夏你将来肯定会拥有惊人的母性，有着巨大的潜力」"
    },
    {
        "name": "セシア",
        "message": "「但是，你现在还不是妈妈。要说为什么的话——」"
    },
    {
        "name": "セシア",
        "message": "「因为你现在所做的，不是妈妈，而是姐姐哦」"
    },
    {
        "name": "サーシャ",
        "message": "「姐姐，大受打击！」"
    },
    {
        "name": "セシア",
        "message": "「你看，就连现在，你都把自己说成是姐姐不是吗。如果不从这里开始改变的话，莎夏你是当不成妈妈的哦」"
    },
    {
        "name": "サーシャ",
        "message": "「呜呜……但是，我要是再也不是大家的姐姐了，那我该怎么活下去才好啊……！？」"
    },
    {
        "name": "*S-1069001_a_3_2",
        "message": "有那么值得烦恼吗！？"
    },
    {
        "name": "セシア",
        "message": "「就是这么回事哦，莎夏。你只是想被我称呼为妈妈，却没有发自内心地想要成为真正的妈妈」"
    },
    {
        "name": "セシア",
        "message": "「你其实是想成为大家的姐姐哦」"
    },
    {
        "name": "セシア",
        "message": "「但是，就像我刚才说的，你作为妈妈有着巨大的潜力。恐怕――」"
    },
    {
        "name": "セシア",
        "message": "「等到你怀上自己的孩子，开始养育他时，母性便会开花结果。现在还不是时候」"
    },
    {
        "name": "セシア",
        "message": "「所以你不用着急，先找到自己心中的爱，然后慢慢培养它吧」"
    },
    {
        "name": "セシア",
        "message": "「这些积累，总有一天会变成巨大的芭比能量」"
    },
    {
        "message": "说完，赛西娅温柔地摸了摸莎夏小姐的头。"
    },
    {
        "name": "サーシャ",
        "message": "「总，总感觉我从赛西娅身上感受到了母性……！」"
    },
    {
        "name": "セシア",
        "message": "「呵呵，虽然身体很小，但我可是爱着整个世界的守护天使哦。就连莎夏你，我也像对待自己的孩子一样爱着呢」"
    },
    {
        "name": "マトイ",
        "message": "「我回来了～咦？」"
    },
    {
        "name": "マトイ",
        "message": "「赛西娅酱，你来了啊。你好～今天怎么了？」"
    },
    {
        "name": "セシア",
        "message": "「缠妈妈～♪ 赛西娅想见妈妈，就来玩了～♪」"
    },
    {
        "name": "*S-1069001_a_3_3",
        "message": "缠妈妈！？"
    },
    {
        "name": "サーシャ",
        "message": "「充满母性的赛西娅酱，一下子进入撒娇模式了！ 啊～！ 小缠，好狡猾啊～！」"
    },
    {
        "name": "マトイ",
        "message": "「不是，就算你这么说……话说回来，我依旧是被赛西娅酱判定为妈妈的那类人啊……」"
    },
    {
        "name": "マトイ",
        "message": "「那个，赛西娅酱。为什么我是妈妈呢……？」"
    },
    {
        "name": "セシア",
        "message": "「嗯～？ 你不当妈妈的理由有很多，但你当妈妈不需要理由哦」"
    },
    {
        "name": "セシア",
        "message": "「并不是因为有母性，所以才是妈妈哦――」"
    },
    {
        "name": "セシア",
        "message": "「而是因为有妈妈在，所以才会产生母性哦♪」"
    },
    {
        "name": "*S-1069001_a_3_4",
        "message": "结果还是不明所以的判定吗……？"
    },
    {
        "name": "セシア",
        "message": "「居然不明白缠妈妈的母性，会长你眼光太差了呢」"
    },
    {
        "name": "マトイ",
        "message": "「不是，我自己也是一头雾水啊……」"
    },
    {
        "name": "セシア",
        "message": "「那个，我就是喜欢这种自然而然散发出来的母性♪」"
    },
    {
        "name": "サーシャ",
        "message": "「果然好羡慕啊～！ 小缠，教教我怎么散发母性吧～！」"
    },
    {
        "name": "マトイ",
        "message": "「等等，莎夏小姐，就算你这么说，我也不知道该怎么教啊！」"
    },
    {
        "name": "セシア",
        "message": "「盯～……」"
    },
    {
        "message": "我突然发现赛西娅正目不转睛地盯着我。我问她怎么了――"
    },
    {
        "name": "セシア",
        "message": "「嗯～会长果然不是我的妈妈呢」"
    },
    {
        "name": "セシア",
        "message": "「这是为什么呢……？」"
    },
    {
        "name": "*S-1069001_a_3_5",
        "message": "不就是因为我是男的吗！？"
    },
    {
        "name": "セシア",
        "message": "「不，妈妈和性别没有关系。你也有成为我妈妈的可能性哦」"
    },
    {
        "message": "看来要理解赛西娅的妈妈判定标准，还需要很长一段时间啊――"
    }
]