[
    {
        "name": "Title",
        "message": "第4话, 爱豆的恋爱练习,P"
    },
    {
        "message": "蕾米卡的现任制作人，其实是我以前做过的兼职——爱豆的助理经理时照顾过我的人。"
    },
    {
        "message": "通过这层关系，我被任命为蕾米卡的代理制作人，工作顺利完成了――"
    },
    {
        "name": "レミカ",
        "message": "「会长，1天制作人辛苦了。手脚非常利落，帮了大忙了」"
    },
    {
        "name": "レミカ",
        "message": "「多亏了你，电影的宣传拍摄，我觉得非常完美」"
    },
    {
        "name": "*S-1060001_a_4_1",
        "message": "在学园拍摄什么的，完全没想到"
    },
    {
        "name": "レミカ",
        "message": "「电影的原作是少女漫画，而且拍摄地点正好是我上学的地方，所以吧」"
    },
    {
        "name": "レミカ",
        "message": "「――嗯？　什么，会长？　有想问的事情吗……」"
    },
    {
        "name": "*S-1060001_a_4_2",
        "message": "蕾米卡，该不会有什么烦恼吧？"
    },
    {
        "name": "レミカ",
        "message": "「哎？　为什么会这么想――今天1天工作看下来，感觉你有点不安」"
    },
    {
        "name": "レミカ",
        "message": "「原来如此……会长你果然能看出来啊……」"
    },
    {
        "name": "レミカ",
        "message": "「这次的电影，原作是少女漫画吧？　所以，主人公的女孩子和男孩子的恋爱，会成为故事的主线」"
    },
    {
        "name": "レミカ",
        "message": "「不过我，恋爱经验一次都没有，甚至连对某个男孩子产生恋爱感情的经历都没有……」"
    },
    {
        "name": "レミカ",
        "message": "「虽然很丢脸，但恋爱这种东西完全不懂」"
    },
    {
        "name": "レミカ",
        "message": "「尽管如此，因为我符合主人公的形象，所以热情地邀请了我，所以我想尽量回应他们的期待」"
    },
    {
        "name": "*S-1060001_a_4_3",
        "message": "如果我能帮上忙，什么都可以商量"
    },
    {
        "name": "レミカ",
        "message": "「谢谢，会长。正在想办法掌握恋爱的感觉……对了」"
    },
    {
        "name": "レミカ",
        "message": "「会长，你接下来还有时间吗？　正好，这种事情除了会长以外没法拜托——」"
    },
    {
        "name": "レミカ",
        "message": "「和我约会，可以吗？」"
    },
    {
        "name": "レミカ",
        "message": "「啊，不，不过，这纯粹是为了获得恋爱的形象，作为爱豆的工作所需的练习」"
    },
    {
        "name": "レミカ",
        "message": "「――可以吗？　那，呃。首先……手牵手，走路的练习吧」"
    },
    {
        "name": "レミカ",
        "message": "「……好。那会长，把手伸出来……牵住了。嗯……」"
    },
    {
        "name": "レミカ",
        "message": "（会长的手，温暖……而且比我想象中大……这就是男孩子的手啊……）"
    },
    {
        "name": "レミカ",
        "message": "（呃，我……紧张吗？　和会长在一起已经习惯了，可是手一碰到就心跳加速……）"
    },
    {
        "name": "レミカ",
        "message": "「那、这样在学园里走走也可以吧？　这个时间学生几乎都走了，不用担心被人看见……」"
    },
    {
        "name": "レミカ",
        "message": "「夜晚的校舎果然很安静啊……」"
    },
    {
        "name": "レミカ",
        "message": "（安静到能听到彼此的呼吸声。自己的心跳声也很在意……会长有没有发现我紧张了呢？）"
    },
    {
        "name": "レミカ",
        "message": "（眼、眼神一对上就觉得会被发现，看不下去……话说我流汗了吗？　这、这太丢人了……）"
    },
    {
        "name": "レミカ",
        "message": "「总之……手牵手的感觉明白了吧，嗯。先到这里为止就可以了――」"
    },
    {
        "name": "レミカ",
        "message": "「啊……」"
    },
    {
        "name": "レミカ",
        "message": "（手一放开，温暖就消失了，感觉有点寂寞……虽然心跳加速，但再多牵一会儿也不错……）"
    },
    {
        "name": "レミカ",
        "message": "「啊？　不、没什么。继续下一步吧」"
    },
    {
        "name": "レミカ",
        "message": "「接下来，电影里有个场景，想练习一下搂腰」"
    },
    {
        "name": "レミカ",
        "message": "「……好。那会长，借你的手臂一下。嗯――」"
    },
    {
        "name": "レミカ",
        "message": "（这、这和牵手完全不同……！？　身体贴在一起，心跳声会传过去吧……）"
    },
    {
        "name": "レミカ",
        "message": "「……！　对、对不起会长，等一下！　稍微离开一下冷静一下……啊！　脚绊到桌子了――」"
    },
    {
        "name": "*S-1060001_a_4_4",
        "message": "哦哦……没事吧？"
    },
    {
        "name": "レミカ",
        "message": "（啊……差点摔倒，被会长抱住了……比刚才更贴近了……）"
    },
    {
        "name": "レミカ",
        "message": "（会长看起来很瘦，但其实身体很结实，力量很强，心跳加速……）"
    },
    {
        "name": "レミカ",
        "message": "（搂腰的时候吓了一跳，但这样贴在一起，感觉到和牵手时一样的温暖……可能会感到安心吧）"
    },
    {
        "name": "レミカ",
        "message": "（这就是男生——会长的感觉啊……）"
    },
    {
        "name": "*S-1060001_a_4_5",
        "message": "蕾米卡，心情平静下来了吗？"
    },
    {
        "name": "レミカ",
        "message": "「啊！？　啊、嗯……已经没事了」"
    },
    {
        "name": "レミカ",
        "message": "（话说，我没时间担心这些……会长也像我一样心跳加速吗？　这……）"
    },
    {
        "name": "レミカ",
        "message": "「――啊、那个……会长。会长……和我牵手或者搂着手臂，不会感到心跳加速吗？啊，不，我并不是说我有这种感觉，只是……」"
    },
    {
        "name": "*S-1060001_a_4_6",
        "message": "我会心跳加速的"
    },
    {
        "name": "レミカ",
        "message": "「――因为害羞，所以装作没有看到？嗯，原来是这样啊……」"
    },
    {
        "name": "レミカ",
        "message": "（听到这句话……有点高兴呢）"
    },
    {
        "name": "レミカ",
        "message": "「嗯，会长怎么了？看起来很惊讶的样子……」"
    },
    {
        "name": "レミカ",
        "message": "「――是因为我比工作的时候笑得更开心吗？唔，骗人……」"
    },
    {
        "message": "蕾米卡一边捏着脸颊，一边露出刚才那种让人心跳加速的笑容，我也不得不意识到自己的脸变得很热。――"
    }
]