[
    {
        "name": "Title",
        "message": "第3话　抓住翘课大王！,P"
    },
    {
        "message": "今天我和菲欧娜两个人聚在一起，进行会长之间的定期报告。"
    },
    {
        "message": "两所学园的星骑士们出动了多少人，取得了怎样的成果——这可是事关今后合作的重要业务。"
    },
    {
        "name": "アポロ",
        "message": "「我说你们俩，还没完吗？　就不能随便应付一下赶快完事吗？」"
    },
    {
        "name": "フィオナ",
        "message": "「姐姐。星徒会的业务可不是儿戏，不能随便应付了事」"
    },
    {
        "name": "アポロ",
        "message": "「可是，流星那些家伙天天都在玩啊」"
    },
    {
        "name": "フィオナ",
        "message": "「大家他们——……等回去后我会和他们谈谈的」"
    },
    {
        "name": "アポロ",
        "message": "「话说，这房间是不是有点冷啊？　感觉特别冷」"
    },
    {
        "name": "*S-ch10040043-1",
        "message": "暖气坏了"
    },
    {
        "name": "*S-ch10040043-1",
        "message": "火炉坏了"
    },
    {
        "name": "アポロ",
        "message": "「──这也太乱了吧！　真亏你们能在这种地方工作……」"
    },
    {
        "name": "フィオナ",
        "message": "「只要忍到工作做完就行了嘛」"
    },
    {
        "name": "フィオナ",
        "message": "「话说回来，琉璃艾尔她们好慢啊……」"
    },
    {
        "name": "アポロ",
        "message": "「你把琉璃也叫来了？」"
    },
    {
        "name": "フィオナ",
        "message": "「是呀，我拜托她来帮忙了。悠莉和喵利昂也是。她们答应说——如果能来的话就尽量来」"
    },
    {
        "name": "フィオナ",
        "message": "「教室里也没找到她们的人，说不定是被叫到办公室去了呢……？」"
    },
    {
        "name": "*S-ch10040043-2",
        "message": "维纳斯她们……"
    },
    {
        "name": "*S-ch10040043-2",
        "message": "这边也"
    },
    {
        "name": "フィオナ",
        "message": "「会长也是？　你也拜托维纳斯她们来帮忙了呀。竟然都迟到了，是发生什么事了吗」"
    },
    {
        "name": "フィオナ",
        "message": "「或许大家都一样忙吧。虽然辛苦，但也只能我们几个自己加油了」"
    },
    {
        "name": "アポロ",
        "message": "「星徒会长这活儿还真是不好干啊。职位高是挺好，但工作太忙可就难办了～」"
    },
    {
        "name": "アポロ",
        "message": "「嗯……对了！　我说我说，等手头忙完后我们去沙滩吧！」"
    },
    {
        "name": "フィオナ",
        "message": "「沙滩——你是说莉普小姐的那片沙滩？」"
    },
    {
        "name": "アポロ",
        "message": "「是啊！　稍微去一会儿就行！　你想啊，星徒会室不是设置了能去度假胜地的传送门吗？」"
    },
    {
        "name": "アポロ",
        "message": "「一直窝在这么冷的房间里会感冒的——放松一下也很重要！　你说是吧，魔王？」"
    },
    {
        "name": "*S-ch10040043-3",
        "message": "稍微去一会儿的话"
    },
    {
        "name": "*S-ch10040043-3",
        "message": "确实可以……"
    },
    {
        "name": "アポロ",
        "message": "「——好，那就走吧！　就这么定了！」"
    },
    {
        "name": "フィオナ",
        "message": "「真是的。我就留在这里处理自己的业务了——你们过一会儿就回来哦」"
    },
    {
        "name": "アポロ",
        "message": "「嘿嘿！　一直窝在房间里果然会憋得慌啊！」"
    },
    {
        "name": "アポロ",
        "message": "「果然，人生最重要的就是偶尔放松一下——嗯？　哎呀……对面也有几个人呢」"
    },
    {
        "name": "ヴィーナス",
        "message": "「上吧，莎夏同学！　必杀射击！」"
    },
    {
        "name": "サーシャ",
        "message": "「太棒了，小维纳斯。看招，回敬你一枪～！」"
    },
    {
        "name": "アポロ",
        "message": "「喂。你们在干嘛呢？」"
    },
    {
        "name": "ヴィーナス",
        "message": "「哎呀，这不是阿波罗嘛。我们在用水枪玩水中生存游戏。你也想加入吗？」"
    },
    {
        "name": "*S-ch10040043-4",
        "message": "那星徒会定期报告会的协助工作呢？"
    },
    {
        "name": "ヴィーナス",
        "message": "「呃——你，你也在这里！？　为什么——」"
    },
    {
        "name": "ヴィーナス",
        "message": "「啊……嗯……我，我们当然没有忘记啦！　对吧，莎夏同学！？」"
    },
    {
        "name": "サーシャ",
        "message": "「是呀，当然啦。我们只是稍微被夏天的热情气氛吸引过来了而已。绝对不是因为星徒会室的暖炉坏了才逃到这里来的哦～」"
    },
    {
        "name": "アポロ",
        "message": "「唔唔唔！　你们两个——是“惯犯”对吧！？　我要把你们抓起来了，魔王！」"
    },
    {
        "name": "*S-ch10040043-5",
        "message": "别想逃"
    },
    {
        "name": "*S-ch10040043-5",
        "message": "明白"
    },
    {
        "name": "ヴィーナス",
        "message": "「呃……！　没想到居然会被阿波罗抓到……！」"
    },
    {
        "name": "サーシャ",
        "message": "「太大意了～」"
    },
    {
        "name": "アポロ",
        "message": "「菲欧娜在星徒会室等着呢，你们俩也快点过去吧！」"
    },
    {
        "name": "アポロ",
        "message": "「真是的，那两人也真够让人头疼的」"
    },
    {
        "name": "アポロ",
        "message": "「我们也不能一直在这里休息，回去之后得给菲欧娜帮忙才行」"
    },
    {
        "name": "アポロ",
        "message": "「在那之前，先去海之家补充一下水分——嗯……？」"
    },
    {
        "name": "ルリエル",
        "message": "「嘿——咻！　看我再给你多添点沙子，这下喵莉昂同学的整个身体都要被埋起来了！」"
    },
    {
        "name": "ニャリオン",
        "message": "「喵！？身，身体完全动不了了喵！」"
    },
    {
        "name": "ユウリ",
        "message": "「哈哈，说到海滩果然就少不了这个啊！」"
    },
    {
        "name": "セーラ",
        "message": "「以喵莉昂的体型，很容易就能埋住呢～」"
    },
    {
        "name": "アポロ",
        "message": "「哔哔——！　发现三个人和一只猫在偷懒！　快点回去帮菲欧娜的忙！」"
    },
    {
        "name": "ルリエル",
        "message": "「啊！？　你怎么会在这里！？」"
    },
    {
        "name": "ユウリ",
        "message": "「糟糕，被发现了」"
    },
    {
        "name": "セーラ",
        "message": "「看来只能溜之大吉了」"
    },
    {
        "name": "ニャリオン",
        "message": "「喵！　居然把被埋起来的本喵丢下不管，真是毫无人性喵！！」"
    },
    {
        "name": "アポロ",
        "message": "「真可怜啊，喵莉昂。我会把你挖出来的，快回星徒会室吧」"
    },
    {
        "name": "ニャリオン",
        "message": "「喵……本喵可不想回星徒会室喵」"
    },
    {
        "name": "ニャリオン",
        "message": "「虽然本喵也被菲欧娜小姐带去了那里……但对猫来说那里的寒气实在是太难忍受了喵！　至少等暖气修好之后再说——」"
    },
    {
        "name": "アポロ",
        "message": "「别啰嗦了！　重要的星徒会工作？　什么来着！　虽然我也不太清楚你在做什么啦！」"
    },
    {
        "name": "アポロ",
        "message": "「不过我也不会放跑那些家伙！　一起抓住他们吧，魔王！」"
    },
    {
        "name": "*S-ch10040043-6",
        "message": "把所有人都送还"
    },
    {
        "name": "*S-ch10040043-6",
        "message": "哦"
    },
    {
        "name": "アポロ",
        "message": "「呼……总算是搞定了，魔王」"
    },
    {
        "name": "アポロ",
        "message": "「不过，还真是群厚脸皮的家伙。没想到星徒会里居然潜伏着这么多翘班魔……」"
    },
    {
        "name": "*S-ch10040043-7",
        "message": "这都多亏了你"
    },
    {
        "name": "*S-ch10040043-7",
        "message": "谢谢"
    },
    {
        "name": "アポロ",
        "message": "「哦！　那我就先回去把剩下的工作干完吧！　我在菲欧娜那里等你哦！」"
    },
    {
        "message": "说完，阿波罗就返回了星徒会室……。"
    },
    {
        "name": "アナ",
        "message": "「……啊」"
    },
    {
        "name": "アナ",
        "message": "「被发现了……不……那个……呃……咳咳」"
    },
    {
        "name": "アナ",
        "message": "「辛苦了，会长」"
    },
    {
        "name": "*S-ch10040043-8",
        "message": "嘴边沾着酱"
    },
    {
        "name": "*S-ch10040043-8",
        "message": "安娜……"
    },
    {
        "name": "アナ",
        "message": "「…………」"
    },
    {
        "name": "アナ",
        "message": "「请看，夕阳正沉入水平线。真美啊……」"
    },
    {
        "message": "连认真的安娜都被蛊惑了，度假胜地的魔力真是可怕。"
    },
    {
        "message": "今天就是让人有这种感觉的一天……。"
    }
]