[
    {
        "message": "集训第二天的晚上。"
    },
    {
        "message": "我们按照安娜的提议，再次举办娱乐活动。――"
    },
    {
        "name": "アナ",
        "message": "「这次，事先请来帮忙的莉普露小姐也参加了」"
    },
    {
        "name": "リップル",
        "message": "「Raschase♪ 我腾出时间，来玩了哦～！」"
    },
    {
        "name": "サーシャ",
        "message": "「小莉普露，欢迎你哦～♪」"
    },
    {
        "name": "リップル",
        "message": "「非常感谢～♪ 我一直想参加集训呢，好开心～！」"
    },
    {
        "name": "サーシャ",
        "message": "「那么，小安娜。关于娱乐活动的内容，我还没听到过呢，要玩些什么呢？」"
    },
    {
        "name": "アナ",
        "message": "「那么，莉普露小姐也来了，我就发表一下吧」"
    },
    {
        "name": "アナ",
        "message": "「这次简而言之就是——」"
    },
    {
        "name": "アナ",
        "message": "「我想来玩试胆」"
    },
    {
        "name": "リップル",
        "message": "「惊悚片是夏天的必备节目呢～」"
    },
    {
        "name": "アナ",
        "message": "「如你所知，莉普小姐可以在结界内制造出各种各样的东西。这次我请她帮忙的是……」"
    },
    {
        "name": "リップル",
        "message": "「制作试胆大会的妖怪～♪」"
    },
    {
        "name": "サーシャ",
        "message": "「哎呀～♪听起来很有趣呢～」"
    },
    {
        "name": "リップル",
        "message": "「呵呵呵，我会让你们大吃一惊的，敬请期待吧！」"
    },
    {
        "name": "アナ",
        "message": "「路线也已经决定好了，我们立刻开始吧。」"
    },
    {
        "message": "就这样，我们沿着试胆大会的路线前进。――"
    },
    {
        "name": "サーシャ",
        "message": "「哎呀？草丛里好像有什么东西跑出来了～」"
    },
    {
        "name": "リップル",
        "message": "「呵呵呵……我制作的恐怖妖怪终于出现了！」"
    },
    {
        "name": "？？？",
        "message": "「吼噜噜噜噜……！」"
    },
    {
        "name": "アナ",
        "message": "「这，这是……」"
    },
    {
        "name": "犬？",
        "message": "「汪！」"
    },
    {
        "name": "リップル",
        "message": "「我来介绍一下！ 这是恐怖的僵尸犬，被它咬到的话就会变成僵尸哦～♪」"
    },
    {
        "name": "*S-event2_002_6_1",
        "message": "这不是鬼怪啊！"
    },
    {
        "name": "リップル",
        "message": "「哎，是这样吗？ 我之前在恐怖电影里看过，还以为是鬼怪呢……」"
    },
    {
        "name": "リップル",
        "message": "「——好像是叫什么危机来着……？ 这么说来，好像确实是叫这个名字……」"
    },
    {
        "name": "アナ",
        "message": "「话说莉普小姐，你刚才说被咬到的话会怎么样……？」"
    },
    {
        "name": "リップル",
        "message": "「嗯？ 虽然只是暂时性的，但被咬到之后肯定会变成僵尸哦～♪ 毕竟它是僵尸犬嘛！」"
    },
    {
        "name": "*S-event2_002_6_2",
        "message": "好可怕好可怕好可怕！"
    },
    {
        "name": "アナ",
        "message": "「居，居然还有这种物理性的恐怖……！ （瑟瑟发抖）……」"
    },
    {
        "name": "サーシャ",
        "message": "「哎呀哎呀，呵呵呵♪ 体验僵尸好像很有趣呢～」"
    },
    {
        "name": "アナ",
        "message": "「啥！？ 莎夏学姐不害怕吗……？」"
    },
    {
        "name": "サーシャ",
        "message": "「嗯～和虫子比起来，应该完全不害怕吧？」"
    },
    {
        "name": "アナ",
        "message": "「诶诶……」"
    },
    {
        "name": "リップル",
        "message": "「顺带一提，这次的僵尸狗是带有花香味的特别款哦～！」"
    },
    {
        "name": "*S-event2_002_6_3",
        "message": "为啥是花香味！？"
    },
    {
        "name": "リップル",
        "message": "「毕竟现在是夏天，感觉腐烂的味道NG呢～」"
    },
    {
        "name": "アナ",
        "message": "「被咬了变成僵尸不也NG吗……！？」"
    },
    {
        "name": "リップル",
        "message": "「啊哈哈！没问题的哦～♪ 僵尸化只是暂时的，不会危害到健康！」"
    },
    {
        "name": "ゾンビ犬",
        "message": "「汪！」"
    },
    {
        "name": "リップル",
        "message": "「啊呜！？ 糟糕了……只顾着说明，疏忽大意了……！」"
    },
    {
        "name": "アナ",
        "message": "「哎……那个，莉普小姐？」"
    },
    {
        "name": "リップル",
        "message": "「很遗憾，僵尸1号就是我了……被狗咬到脚了……」"
    },
    {
        "name": "リップル",
        "message": "「那么各位，加油从僵尸狗和我手中逃掉吧……Good luck……！」"
    },
    {
        "name": "*S-event2_002_6_4",
        "message": "制作人第一个先挂了————！？"
    },
    {
        "name": "サーシャ",
        "message": "「哎呀～♪」"
    },
    {
        "name": "アナ",
        "message": "「啊哇哇……不不，这下，到底该怎么办啊……！？」"
    },
    {
        "name": "ゾンビ犬",
        "message": "「咕噜噜噜……汪！」"
    },
    {
        "name": "アナ",
        "message": "「呜哇哇！？ 朝这边来了！？」"
    },
    {
        "name": "アナ",
        "message": "「我被盯上了！？ 等一下，别过来啊……！」"
    },
    {
        "name": "ゾンビ犬",
        "message": "「我……要咬你……！ 要把你，咬成碎片……！」"
    },
    {
        "name": "*S-event2_002_6_5",
        "message": "它说话了——————！！？"
    },
    {
        "name": "アナ",
        "message": "「会说话好恐怖！ 而且跑得好快……！ 逃不掉了……！」"
    },
    {
        "name": "サーシャ",
        "message": "「它跑得太快，就算想拦也拦不住呢～」"
    },
    {
        "name": "アナ",
        "message": "「啊哇哇哇，被逼到绝境了……！ 靠近一看，它的眼睛都快掉出来了，还有一部分内脏跑到了外面，好恶心……！」"
    },
    {
        "name": "アナ",
        "message": "「啊，不过它身上的花香味真的好浓郁，闻着就让人觉得很安心……啊」"
    },
    {
        "name": "ゾンビ犬",
        "message": "「汪！」"
    },
    {
        "name": "アナ",
        "message": "「浓郁的花香味反而成了陷阱……哦呼」"
    },
    {
        "name": "*S-event2_002_6_6",
        "message": "安娜被咬了——————！"
    },
    {
        "name": "ゾンビ犬",
        "message": "「咕噜噜……接下来，我要和你们一起玩……！」"
    },
    {
        "name": "サーシャ",
        "message": "「哎呀哎呀，狗狗，这次的目标是我们呢～」"
    },
    {
        "name": "サーシャ",
        "message": "「不，不只是狗狗——」"
    },
    {
        "name": "リップル",
        "message": "「会长和莎夏也是……僵尸欢迎你哦～」"
    },
    {
        "name": "アナ",
        "message": "「No problem……习惯以后就不怕了哦……？」"
    },
    {
        "name": "サーシャ",
        "message": "「你们两个都变成僵尸了呢～♪」"
    },
    {
        "name": "リップル",
        "message": "「啊哈哈～」"
    },
    {
        "name": "アナ",
        "message": "「咪嚓……」"
    },
    {
        "name": "*S-event2_002_6_7",
        "message": "空洞的笑容好吓人好吓人好吓人！"
    },
    {
        "name": "ゾンビ犬",
        "message": "「不会让你逃掉的……汪！」"
    },
    {
        "name": "サーシャ",
        "message": "「哎呀哎呀，呵呵呵♪ 转眼间就被包围了呢～」"
    },
    {
        "name": "サーシャ",
        "message": "「——明明身处大危机却还这么冷静……？ 不对，会长君，应该说是相反哦～」"
    },
    {
        "name": "サーシャ",
        "message": "「正因为身处危机才更让人激动不已，反而更有意思呢～试胆大会这种活动，其实我超喜欢的哦～♪」"
    },
    {
        "name": "サーシャ",
        "message": "「——要怎样才能摆脱这种状况呢？ 我倒是想到了一个或许能行的办法哦～」"
    },
    {
        "name": "サーシャ",
        "message": "「不行的话就算了，变成僵尸体验一下好像也挺有趣的，那就试试看吧♪」"
    },
    {
        "name": "サーシャ",
        "message": "「呐，小狗狗。你刚才说要跟我们玩，难道是想跟我们搞好关系吗？」"
    },
    {
        "name": "ゾンビ犬",
        "message": "「没错……所以，咬一口变成僵尸……那样的话，就能搞好关系……」"
    },
    {
        "name": "サーシャ",
        "message": "「原来如此呢～但是姐姐我啊，要是被你咬了的话就没办法抱紧你，也没办法夸你是个好孩子了哦～」"
    },
    {
        "name": "ゾンビ犬",
        "message": "「姐姐……？ 夸我是个好孩子……？」"
    },
    {
        "name": "サーシャ",
        "message": "「所以说～看招♪」"
    },
    {
        "name": "*S-event2_002_6_8",
        "message": "莎夏主动抱住了僵尸狗！？"
    },
    {
        "name": "サーシャ",
        "message": "「好～乖好乖好乖♪ 小狗狗，好孩子好孩子～♪」"
    },
    {
        "name": "ゾンビ犬",
        "message": "「汪！？ 你干什么……！？ 你不怕我这个僵尸吗……！？」"
    },
    {
        "name": "サーシャ",
        "message": "「嗯～？ 虽然有点个性，但跟独角仙比起来还是挺可爱的嘛～？ 而且还有股花香味，姐姐我很喜欢哦～♪」"
    },
    {
        "name": "サーシャ",
        "message": "「所以别再咬人了，跟姐姐我好好地玩吧♪ 好不好？」"
    },
    {
        "name": "ゾンビ犬",
        "message": "「我，我可是……僵尸……怎么可能跟咬了人的家伙好好玩……！」"
    },
    {
        "name": "サーシャ",
        "message": "「好～啦，跟姐姐我来个亲密的拥抱吧～♪ 抱～<emoji=heart04>」"
    },
    {
        "name": "ゾンビ犬",
        "message": "「噢……噢噢噢噢……！」"
    },
    {
        "name": "ゾンビ犬",
        "message": "「……呜～呜<emoji=heart04>」"
    },
    {
        "name": "*S-event2_002_6_9",
        "message": "居然用姐姐的力量收服了它————！！"
    },
    {
        "name": "ゾンビ犬",
        "message": "「我，要听，大姐姐的话……♪」"
    },
    {
        "name": "サーシャ",
        "message": "「好～♪ 那么，小莉普和安娜也来，抱一个<emoji=heart04>」"
    },
    {
        "name": "リップル",
        "message": "「哇哦！？ ……姐姐的拥抱，好BIG好happy～♪」"
    },
    {
        "name": "アナ",
        "message": "「呼哇……Yes，姐姐。你就是神」"
    },
    {
        "name": "サーシャ",
        "message": "「哎呀哎呀，呵呵呵♪ 大家都叫我姐姐，好高兴呀～♪」"
    },
    {
        "name": "サーシャ",
        "message": "「好乖好乖，好孩子好孩子♪」"
    },
    {
        "name": "*S-event2_002_6_10",
        "message": "姐，姐姐无双……！"
    },
    {
        "message": "就这样，试胆大会以莎夏小姐的单独胜利拉下了帷幕――"
    },
    {
        "message": "第二天。安娜和莉普的僵尸化顺利解除了。"
    },
    {
        "name": "リップル",
        "message": "「姐姐，那我今天也在海之家加油干活啦～♪」"
    },
    {
        "name": "サーシャ",
        "message": "「好～，路上小心♪」"
    },
    {
        "name": "アナ",
        "message": "「早上好。今天也要努力生存下去哦」"
    },
    {
        "name": "サーシャ",
        "message": "「安娜，早上好～♪ 今天也要教我很多很多钓鱼的知识哦」"
    },
    {
        "name": "アナ",
        "message": "「好的，姐姐」"
    },
    {
        "name": "*S-event2_002_6_11",
        "message": "不对劲的被传染了——————！！？"
    },
    {
        "name": "サーシャ",
        "message": "「哎呀哎呀，嘻嘻♪」"
    },
    {
        "message": "这恐怖的发展吓得我不由得叫出了声――"
    }
]