[
    {
        "message": "之后，为了搜索在校内遗失的失落之物，我们决定分头寻找。"
    },
    {
        "message": "队伍被分为两组，这一组的成员有莎夏小姐，静羽，还有我。"
    },
    {
        "name": "シズハ",
        "message": "「呵呵，还是第一次像这样和姐姐一起寻找失落之物呢」"
    },
    {
        "name": "サーシャ",
        "message": "「是啊～。而且静羽在进行魔法少女活动这件事，也是完全偶然才知道的」"
    },
    {
        "name": "ディーラック",
        "message": "「嘻嘻♪失落之物是很危险的道具嘛～。要是这么轻易地被很多人知道存在的话，可就糟了呢」"
    },
    {
        "name": "*S-event15_015_4_1",
        "message": "崔吉安娜也是同样的立场啊\n相关人士都是同样的想法啊"
    },
    {
        "name": "シズハ",
        "message": "「如果不是作为小幸的合作者，我就不会像这样认识会长了。真是感谢这偶然的机会呢～♪」"
    },
    {
        "name": "サーシャ",
        "message": "「呵呵呵～。静羽，你心情可真好呢～？」"
    },
    {
        "name": "シズハ",
        "message": "「那当然了。直到不久之前，我都还只能躺在医院的病床上，而现在却能和姐姐以及她的朋友们一起像这样散步呢！」"
    },
    {
        "name": "サーシャ",
        "message": "「哎呀哎呀♪ 玩闹是不错，但可别摔倒了哦？」"
    },
    {
        "name": "シズハ",
        "message": "「哎嘿嘿～我知道啦～哎呦？ 哎呀！」"
    },
    {
        "message": "静羽在空无一物的地方突然绊了一下，但她还是勉强自己站稳了。"
    },
    {
        "name": "サーシャ",
        "message": "「你看，我就说吧。我牵着你的手，你别走在前面了，我们一起走吧？」"
    },
    {
        "name": "シズハ",
        "message": "「没事的，没事的～！ 我的身体已经非常健康了。这只是单纯的运动不足，或者说锻炼不足罢了」"
    },
    {
        "name": "シズハ",
        "message": "「而·且·呢～♪ 如果要和姐姐亲密接触，比起牵手，我更喜欢这种方式哦～」"
    },
    {
        "name": "シズハ",
        "message": "「所以啦。屁股坐♪」"
    },
    {
        "name": "サーシャ",
        "message": "「啊啊嗯<emoji=heart04>」"
    },
    {
        "name": "*S-event15_015_4_2",
        "message": "莎夏小姐……！？"
    },
    {
        "name": "サーシャ",
        "message": "「会长……？ 你怎么了，脸红成这样」"
    },
    {
        "name": "サーシャ",
        "message": "「我的声音……？ 呵呵♪ 因为静羽揉得好熟练，我就忍不住叫出来了～」"
    },
    {
        "name": "シズハ",
        "message": "「我可没有用那么下流的方式揉哦……！？」"
    },
    {
        "name": "シズハ",
        "message": "「啊啊啊，会长和迪酱都别用那么冰冷的眼神看我啦……！！」"
    },
    {
        "name": "シズハ",
        "message": "「不过……！ 姐姐的屁股又大又软，摸起来肯定很舒服吧！」"
    },
    {
        "name": "*S-event15_015_4_3",
        "message": "果然刚刚那是性骚扰啊……！"
    },
    {
        "name": "シズハ",
        "message": "「不——是——啦！虽然我心里是这么想的，但我把欲望压在心底，这次最多只是摸一摸而已啦！」"
    },
    {
        "name": "サーシャ",
        "message": "「嗯嗯，我觉得静羽对屁股的关心是真心的哦♪」"
    },
    {
        "name": "ディーラック",
        "message": "「嘻嘻。会长正用屁股挡住静羽酱，和她保持距离呢。看来她是再也不想让静羽酱看到自己的背后了」"
    },
    {
        "name": "シズハ",
        "message": "「真是的～～！都怪姐姐发出了奇怪的声音！绝对是故意的吧！」"
    },
    {
        "name": "サーシャ",
        "message": "「才没有那回事呢～♪」"
    },
    {
        "name": "シズハ",
        "message": "「太狡猾了！既然如此，那姐姐也来揉我的屁股！！」"
    },
    {
        "name": "サーシャ",
        "message": "「哎呀～♪ 真是大胆的告白呢～」"
    },
    {
        "name": "サーシャ",
        "message": "「不过比起静羽可爱的屁股，我更喜欢这边呢」"
    },
    {
        "message": "莎夏小姐说着，温柔地抚摸静羽的头。"
    },
    {
        "name": "シズハ",
        "message": "「啊呜呜……姐姐你个笨蛋。这样不就像只有我一个人是变态了吗」"
    },
    {
        "name": "サーシャ",
        "message": "「哎呀哎呀。那我要不要停下呢……？」"
    },
    {
        "name": "シズハ",
        "message": "「那也不行……姐姐就是姐姐，你要更多地宠着我啊」"
    },
    {
        "name": "サーシャ",
        "message": "「当然没问题啦～只要你想要，要我摸你的头多久都可以哦<emoji=heart04>」"
    },
    {
        "name": "*S-event15_015_4_4",
        "message": "哈～大饱眼福，大饱眼福"
    },
    {
        "name": "ディーラック",
        "message": "「……你们两个，玩闹是无所谓，但等告一段落之后也要认真找失落之物哦？」"
    }
]