[
    {
        "name": "Title",
        "message": "第8话,灾厄之手,B"
    },
    {
        "name": "アポロ",
        "message": "「唔唔唔——！！」"
    },
    {
        "name": "クロト",
        "message": "（这不是星术——是另一种力量——）"
    },
    {
        "name": "アナ",
        "message": "（——难道）"
    },
    {
        "name": "アイリーン",
        "message": "「哈啊，哈啊……这次一定要成功！」"
    },
    {
        "name": "セドナ",
        "message": "「辛苦了」"
    },
    {
        "message": "借助神秘新势力的力量，我们终于把阿波罗逼到了绝境。"
    },
    {
        "message": "一直捣乱的基尔这次也终于倒下了，不会再有人来碍事。"
    },
    {
        "name": "ネビュラ隊員Ａ",
        "message": "「准备射击——！」"
    },
    {
        "message": "她们排着整齐的队列，各自架起了独特的枪支。"
    },
    {
        "message": "是想让她彻底无力化。"
    },
    {
        "name": "エリシア",
        "message": "「——姐姐……！」"
    },
    {
        "name": "クロト",
        "message": "「唔……请等等！ 那东西，有着她姐姐的外形——！」"
    },
    {
        "name": "セドナ",
        "message": "「很抱歉，没有同情的余地。动手」"
    },
    {
        "name": "ネビュラ隊員Ｂ",
        "message": "「是！！」"
    },
    {
        "name": "エリシア",
        "message": "「……！」"
    },
    {
        "message": "艾莉西雅没有阻止他们，只是默默闭上眼睛。"
    },
    {
        "message": "就算有着姐姐的外形，作为世界的威胁而被消灭也是没有办法的……"
    },
    {
        "message": "──然而。"
    },
    {
        "name": "ネビュラ隊員Ａ",
        "message": "「哎……？」"
    },
    {
        "name": "ネビュラ隊員Ｂ",
        "message": "「目……目标，增加了……？」"
    },
    {
        "message": "她们的扫射被阻挡了。"
    },
    {
        "message": "一个神秘的存在出现在那里，为晕倒的阿波罗搭建起屋顶。"
    },
    {
        "name": "ネビュラ隊員Ａ",
        "message": "「那……那是什么……」"
    },
    {
        "name": "アイリーン",
        "message": "「手……？ 看起来像是手……？」"
    },
    {
        "name": "セドナ",
        "message": "「……」"
    },
    {
        "message": "没错，那是一只<ruby=・>手</ruby>。"
    },
    {
        "message": "除此之外无从形容，就只是一只大得离谱的手。"
    },
    {
        "message": "那只手缓缓地包住阿波罗，像是在守护他。"
    },
    {
        "name": "アポロ",
        "message": "「……」"
    },
    {
        "message": "而阿波罗本人仿佛正在摇篮中摇荡。"
    },
    {
        "message": "失去意识的她，睡脸看上去就是个与年龄相符的纯真少女。"
    },
    {
        "name": "エリシア",
        "message": "「姐，姐……？」"
    },
    {
        "message": "艾莉西雅摇摇晃晃地喊了她一声。"
    },
    {
        "message": "接着，手弹起了中指。"
    },
    {
        "message": "也就是，弹额头。"
    },
    {
        "message": "然后──"
    },
    {
        "name": "セドナ",
        "message": "「唔——」"
    },
    {
        "name": "アイリーン",
        "message": "「什——咕啊！？」"
    },
    {
        "name": "エリシア",
        "message": "「唔唔唔————！！」"
    },
    {
        "name": "ニャリオン",
        "message": "「艾莉西雅小姐——！！」"
    },
    {
        "message": "被直接命中的艾莉西雅，被飓风刮到了遥远的彼方。"
    },
    {
        "message": "我们和新出现的她们也受到了余波的影响，差点被地缝吞没。"
    },
    {
        "name": "ユウリ",
        "message": "「菲欧娜也太容易被盯上了吧——！！」"
    },
    {
        "name": "エリシア",
        "message": "「悠莉——」"
    },
    {
        "message": "冲上前去的悠莉展开护盾，保护着艾莉西雅。"
    },
    {
        "message": "但是……阿波罗并没有继续追击。"
    },
    {
        "message": "他只是温柔地把昏过去的阿波罗放了上去……"
    },
    {
        "name": "ギエル",
        "message": "「唔……呼。那……我们先撤退吧……阿波罗，大人」"
    },
    {
        "name": "アポロ",
        "message": "「……」"
    },
    {
        "message": "站起来的基尔也跟着一起，手臂向夜空升起。"
    },
    {
        "name": "ネビュラ隊員Ｂ",
        "message": "「快逃！」"
    },
    {
        "name": "セドナ",
        "message": "「瞄准」"
    },
    {
        "name": "アイリーン",
        "message": "「扫射——！」"
    },
    {
        "message": "黑色弹幕被谜之手臂吸收进去，却无法阻止它。"
    },
    {
        "message": "随着陷入沉睡的阿波罗，一同消失在星空的彼方……"
    },
    {
        "name": "エリシア",
        "message": "「菲欧娜——姐姐啊啊啊啊啊啊啊！！！」"
    },
    {
        "message": "唯有那决死的叫喊，始终在夜空中回响。"
    },
    {
        "name": "クロト",
        "message": "「……」"
    },
    {
        "message": "然而……这是为什么呢。"
    },
    {
        "message": "艾莉西雅呼唤的那位叫做菲欧娜的女孩。"
    },
    {
        "message": "看着那只巨大而恐怖的手掌，……"
    },
    {
        "message": "一股难以言喻的寂寞感，在我的内心深处萦绕。"
    }
]