[
    {
        "name": "エンジュ",
        "message": "「我还以为是谁呢，原来是魔王啊……你真是学不乖，每天每天……今天又来干什么？ 如果是要送吃的过来的话，那我就非常欢迎了。把东西放下，然后赶紧滚吧」"
    },
    {
        "message": "起初安洁对我充满了敌意，但随着我们交谈的次数越来越多，彼此之间的隔阂也逐渐消失了。"
    },
    {
        "message": "既然语言能够相通，那只要交谈多次，就能将彼此的想法传达给对方。"
    },
    {
        "message": "不知不觉间，安洁偶尔会露出的可爱一面将我的心紧紧抓住了，而令人高兴的是，她似乎也和我一样。"
    },
    {
        "name": "エンジュ",
        "message": "「你这人真是奇怪……向我这种不可爱的女人求爱到底有什么意思啊……」"
    },
    {
        "name": "エンジュ",
        "message": "「星徒会里明明还有比我漂亮得多，身材也好的多的女人……真是个笨蛋」"
    },
    {
        "name": "クロト",
        "message": "「别说什么“我这种人”啊。我喜欢的，就只有安洁你一个人」"
    },
    {
        "name": "エンジュ",
        "message": "「你真是狡猾……我也，对你……那个……并……并不是讨厌啦」"
    },
    {
        "name": "エンジュ",
        "message": "「毕竟也不知道什么时候我会从这里消失……所以，也算是为了留下一点回忆吧。如果你说喜欢我并非谎言的话——」"
    },
    {
        "name": "エンジュ",
        "message": "「能不能把我变成女人呢……？」"
    },
    {
        "message": "一瞬没反应过来『变成女人』是什么意思，思考停滞了一下，但在理解之后，又因为太过震惊而感觉时间仿佛停止了。"
    },
    {
        "name": "クロト",
        "message": "「哎……真，真的可以吗……？」"
    },
    {
        "name": "エンジュ",
        "message": "「不行的话我怎么会开这种玩笑呢。我也一样，觉得你这个人，甚至可以献出第一次——」"
    },
    {
        "name": "エンジュ",
        "message": "「啊啊，不对，不是那样……至少这种时候，必须要好好说出来才行……」"
    },
    {
        "name": "エンジュ",
        "message": "「我想被心爱的你抱……希望你能在我身上，刻下你的印记」"
    },
    {
        "name": "エンジュ",
        "message": "「虽说我说想被你抱，但这个姿势也太……不就像是让小孩子小便一样吗……！？」"
    },
    {
        "message": "因为安洁说『被你正面盯着看太难为情了』，所以我让她背对着我坐在我的腿上。"
    },
    {
        "name": "クロト",
        "message": "「我也是第一次，不太清楚该插进去哪里……」"
    },
    {
        "name": "エンジュ",
        "message": "「魔王也是第一次吗……？明明身边有那么多漂亮的女孩，你在搞什么啊……我真的可以成为你的第一个女人吗……」"
    },
    {
        "name": "クロト",
        "message": "「第一次的对象，我只想是心爱的安洁啊」"
    },
    {
        "name": "エンジュ",
        "message": "「嗯嗯……<emoji=heart04> 都说了别在我耳边说话……我会起鸡皮疙瘩的……嗯<emoji=heart04> 别太得意忘形──嗯哈啊啊……<emoji=heart04>」"
    },
    {
        "message": "只是在耳边轻声细语，安洁就做出了如此可爱的反应。我把几乎要爆发的勃起肉棒抵在了穴口附近，生怕一个不小心就会射出来。"
    },
    {
        "message": "性器官相互接触，我的预射液和安洁的爱液，双方的分泌液混合在一起，发出轻微的水声。"
    },
    {
        "name": "エンジュ",
        "message": "「啊，啊啊，就是那附近……我的，那个……那里──等，等，等一下……肉棒，有这么大吗！？ 我不觉得它能进得去啊！？」"
    },
    {
        "name": "クロト",
        "message": "「害怕的话，我可以现在就停下来」"
    },
    {
        "name": "エンジュ",
        "message": "「唔……！ 别说蠢话了……都到这一步了，事到如今还说什么……你有办法忍住吗……？」"
    },
    {
        "name": "クロト",
        "message": "「说实话，我现在就想马上和安洁做爱，想得受不了了」"
    },
    {
        "name": "エンジュ",
        "message": "「我想也是──谢谢你这么坦诚地告诉我。我爱你，魔王。收下我的第一次吧……」"
    },
    {
        "name": "エンジュ",
        "message": "「呼，唔，呜呜呜呜呜呜呜呜呜嗯……！？」"
    },
    {
        "message": "我慢慢地放下怀里的安洁，抵在穴口的肉棒，渐渐埋入了温暖潮湿的泥泞中。"
    },
    {
        "name": "エンジュ",
        "message": "「唔！？ 嗯唔，哈，哈啊……里面，好像有什么被扯开了……咿唔咕！？」"
    },
    {
        "message": "阴茎的尖端传来轻微的撕裂某种柔软物体的感触。那恐怕就是安洁的处女之证吧。"
    },
    {
        "name": "クロト",
        "message": "「安洁，你没事吧……？ 会不会痛……？」"
    },
    {
        "name": "エンジュ",
        "message": "「哈啊，哈咿……哈，没事，才怪啦……！ 粗粗的棒子都插进我里面了啊……！ 肯定会痛的吧……！」"
    },
    {
        "message": "接受了我肉棒的安洁张大着嘴，口水从嘴角流下，激烈地喘息着。"
    },
    {
        "message": "我心中对她感到抱歉，但另一方面，成为安洁初次性交对象的喜悦却令我全身颤抖。"
    },
    {
        "name": "エンジュ",
        "message": "「哈啊，哈……但是，这种程度的疼痛和出血我都习惯了……完全，能忍得住……」"
    },
    {
        "name": "エンジュ",
        "message": "「你让我成为了女人的这份痛楚……不可思议地，甚至让我感到了喜悦哦……我一辈子，都不会忘记的，呵呵」"
    },
    {
        "name": "エンジュ",
        "message": "「哈啊，哈……你关心我很让我高兴，不过你自己呢……？ 那个……你的肉棒，有变得舒服吗……？」"
    },
    {
        "name": "クロト",
        "message": "「有啊……你的里面，又热又紧，舒服得不得了……！」"
    },
    {
        "message": "我除了对正在忍耐疼痛的安洁感到抱歉之外，第一次插入的女性器官那充满感官的触感和温暖，也让我一瞬间就沉醉其中。"
    },
    {
        "name": "エンジュ",
        "message": "「嗯……是吗，原来我也可以，对你派上用场啊……哈啊，嗯呜……！」"
    },
    {
        "name": "エンジュ",
        "message": "「只是插进去的话肉棒也不会舒服起来吧……？ 不用在意我的身体。随你喜欢地动吧……」"
    },
    {
        "message": "忍耐已经到达极限的我，顺着她的话将肉棒插得更深。"
    },
    {
        "name": "エンジュ",
        "message": "「嗯啊啊啊啊啊……！ 插得好，深……啊，嗯啊，肚子，被撑开了……这是，什么感觉……！？」"
    },
    {
        "name": "エンジュ",
        "message": "「就好像……你的肉棒……填满了我的里面……被你，染上了你的颜色……呼啊啊嗯……<emoji=heart04>」"
    },
    {
        "name": "エンジュ",
        "message": "「嗯啊……！？ 肉棒在我的里面，胀得更大了……男性的身体，究竟是怎么回事——」"
    },
    {
        "name": "クロト",
        "message": "「安洁，可以拜托你一件事吗？」"
    },
    {
        "name": "エンジュ",
        "message": "「什，什么……？ 都做到这一步了，再拜托个一两件事也——什……！？」"
    },
    {
        "message": "听到我低声说出的请求，安洁的身体猛地一颤。"
    },
    {
        "name": "エンジュ",
        "message": "「你，你真的是个笨蛋啊……不，不过是说几句话而已，也，也没什么……嗯……」"
    },
    {
        "name": "エンジュ",
        "message": "「啊啊……你，你的，肉棒……胀得好大……在摩擦，我的小穴……！」"
    },
    {
        "name": "エンジュ",
        "message": "「真是的……居然说什么『要具体说出性器官的名字』……我的恋人真是个比想象中还要变态的人啊」"
    },
    {
        "name": "クロト",
        "message": "「安洁你一说这些色色的话，就比想象中还要，让我兴奋啊……！」"
    },
    {
        "name": "エンジュ",
        "message": "「哼，哼，只不过是说了几句羞耻的话，你就能兴奋起来的话——嗯啊<emoji=heart04> 肉棒变得越来越硬了……！」"
    },
    {
        "name": "エンジュ",
        "message": "「我的小穴，就那么舒服吗……？真是单纯的家伙……不过这样也有点可爱嘛，呵呵<emoji=heart04>」"
    },
    {
        "name": "エンジュ",
        "message": "「嗯，嗯啊……嗯唔呼……<emoji=heart04> 哎……？等，等一下……你肉棒摩擦的地方……好像，很舒服……？」"
    },
    {
        "message": "当我以某个角度摩擦起安洁肚脐内侧附近时──"
    },
    {
        "name": "エンジュ",
        "message": "「嗯呼啊啊！？<emoji=heart04> 呀，啊，那，那里，是怎么回事……好酥麻，好舒服……<emoji=heart04>」"
    },
    {
        "message": "龟头摩擦着粗糙的阴道壁，无论对于安洁还是我来说，都带来了无上的快感。"
    },
    {
        "name": "エンジュ",
        "message": "「骗，骗人的吧……明明是第一次……居然这么快就舒服起来了……这样不就像是个好色的女人了吗……<emoji=heart04>」"
    },
    {
        "name": "エンジュ",
        "message": "「可不要以为我是因为被你强迫说了下流的话才这样的哦……我才不是那么单纯的女……哈，嗯啊啊……<emoji=heart04>」"
    },
    {
        "name": "クロト",
        "message": "「安洁舒服起来时的可爱声音，我还想再多听听呢」"
    },
    {
        "name": "エンジュ",
        "message": "「什……！ 别说这种让人害羞的话啊！ 我，我，我才不可爱呢……！」"
    },
    {
        "name": "クロト",
        "message": "「很可爱哦，现在的安洁，非常可爱……！」"
    },
    {
        "name": "エンジュ",
        "message": "「笨蛋……不要一直说我可爱，可爱什么的啊……这样会让人误会的啊……不要让我误会啊……啊嗯<emoji=heart04>」"
    },
    {
        "name": "エンジュ",
        "message": "「嗯啊，果然，好舒服……比自己一个人做要舒服多了……嗯啊啊啊<emoji=heart04> 从来都没碰过那里……居然会这么舒服……<emoji=heart04>」"
    },
    {
        "name": "クロト",
        "message": "「安洁也会自慰的吗……！？」"
    },
    {
        "name": "エンジュ",
        "message": "「哈啊……！？ 那，那当然了，我也是，兴奋的时候一个人安慰自己，这种事还是会做的……<emoji=heart04>」"
    },
    {
        "name": "エンジュ",
        "message": "「你不也一个人撸过自己的肉棒吗——噫呜，嗯，呼啊，嗯呼呜呜呜呜<emoji=heart04>」"
    },
    {
        "name": "クロト",
        "message": "「安洁的小穴，比我自己用手撸管舒服多了……」"
    },
    {
        "name": "エンジュ",
        "message": "「呀啊啊……都说了，不要在耳边说悄悄话啦……<emoji=heart04> 我也是……被你的肉棒，操到神志不清了……<emoji=heart04> 呼啊啊……做爱，原来这么刺激的啊……<emoji=heart04>」"
    },
    {
        "name": "エンジュ",
        "message": "「呜，呜呜呜呜呜……求你了，再多，再多，让我的小穴，舒服一点……<emoji=heart04> 我想和你，一起，变得，舒服……<emoji=heart04>」"
    },
    {
        "message": "直到刚才还羞答答的，连性器的名称都不敢说出口，现在却从她那迷乱的嘴里不断溢出。"
    },
    {
        "message": "安洁撒娇的模样实在惹人怜爱，我一边抱起她的身体，一边激烈地向上顶去。"
    },
    {
        "name": "エンジュ",
        "message": "「嗯啊<emoji=heart04> 啊，啊啊<emoji=heart04> 啊，啊，呜啊啊啊啊嗯<emoji=heart04> 不知道，我都不知道有这种事啊<emoji=heart04> 脑袋，要变奇怪了啦，要变奇怪了啦啊啊<emoji=heart04>」"
    },
    {
        "message": "配合着肉棒轻敲子宫口的节奏，她发出了高昂的喘息。"
    },
    {
        "message": "从安洁的喘息声中，已经完全听不出任何羞耻的成分。不光是第一次做爱的快感，看到冷酷的安洁变得如此有感觉，更是让我又惊又喜。"
    },
    {
        "name": "エンジュ",
        "message": "「嗯啊，啊哈，好舒服啊<emoji=heart04> 小穴，小穴好舒服啊<emoji=heart04> 魔王，再来嘛<emoji=heart04> 再用，肉棒多顶几下嘛<emoji=heart04> 把我，把我操坏掉嘛啊啊<emoji=heart04>」"
    },
    {
        "message": "听到这仿佛要将人融化的大胆请求，我将抽插的速度提升到了极限。"
    },
    {
        "name": "エンジュ",
        "message": "「嗯啊啊！？ 好激烈<emoji=heart04> 肉棒，肉棒越来越激烈了<emoji=heart04> 啊，啊，啊，再给我更多快感吧<emoji=heart04>」"
    },
    {
        "message": "每次抽插，白色的泡沫状爱液都会被带出，房间内充满了我和安洁交合的气味。"
    },
    {
        "message": "虽然这个房间可能正在被监视，但不管被谁偷窥，不管被谁妨碍，事到如今我都停不下来了。"
    },
    {
        "name": "エンジュ",
        "message": "「嗯啊，啊，啊<emoji=heart04> 魔王，魔王……<emoji=heart04> 喜欢，最喜欢了……<emoji=heart04> 不管是肉棒，还是做爱，全都最喜欢了……<emoji=heart04>」"
    },
    {
        "message": "第一次做爱就凭着一股冲动，而安洁娇小的身体却能完全接受我的一切，这让我对她充满了怜爱。"
    },
    {
        "name": "エンジュ",
        "message": "「你的肉棒，能用我的小穴变得更舒服，我好开心……♪」"
    },
    {
        "name": "エンジュ",
        "message": "「哈，哈嗯<emoji=heart04> 魔王，我的小穴，舒服吗？能好好射出来吗？能射出精子吗？」"
    },
    {
        "message": "每当摩擦下体发出响亮的水声，快感的电流就会传遍全身。距离极限的到来已经不远了。"
    },
    {
        "name": "エンジュ",
        "message": "「嗯，好棒……<emoji=heart04> 顶我的小穴，变得更加更加舒服吧……魔王的精子，可以全部射到我的里面……<emoji=heart04>」"
    },
    {
        "name": "エンジュ",
        "message": "「全部，全部，射到我的肚子里，射到子宫里……<emoji=heart04> 就这样，我想要，想要魔王的一切……<emoji=heart04>」"
    },
    {
        "name": "エンジュ",
        "message": "「嗯啊啊<emoji=heart04> 还要，还要更多<emoji=heart04> 用力插我<emoji=heart04> 把小穴，插到坏掉，嗯<emoji=heart04> 用力，用力插我<emoji=heart04>」"
    },
    {
        "name": "エンジュ",
        "message": "「啊，哈，呼啊！ 啊，啊嗯，啊嗯……啊啊啊<emoji=heart04> 丢了，丢了……喜欢，喜欢，最喜欢了<emoji=heart04>」"
    },
    {
        "name": "エンジュ",
        "message": "「哈啊，嗯……不要离开我啦<emoji=heart04> 绝对，不要放开我……<emoji=heart04> 小穴好热，呀啊，呀啊<emoji=heart04> 啊，哈啊，嗯啊，啊，啊啊，啊啊啊啊<emoji=heart04>」"
    },
    {
        "message": "我也像在宣告即将高潮一般，用力抱紧撒娇的她，向着最深处一插到底，直击子宫口。"
    },
    {
        "name": "エンジュ",
        "message": "「啊，啊啊，哈啊啊啊嗯<emoji=heart04> 嗯啊<emoji=heart04> 啊<emoji=heart04> 小穴，小穴要去了，要被肉棒操到高潮了<emoji=heart04>」"
    },
    {
        "name": "エンジュ",
        "message": "「嗯啊，呀，呀啊<emoji=heart04> 嗯呼啊，啊啊呜呜<emoji=heart04> 哈啊啊啊嗯<emoji=heart04> 小穴有，有，好厉害的东西来了呜呜<emoji=heart04>」"
    },
    {
        "name": "エンジュ",
        "message": "「呀啊<emoji=heart04> 啊，啊，嗯呜嗯呜嗯呜<emoji=heart04> 丢了，丢了，丢了丢了丢了呜呜呜呜呜呜呜呜呜呜<emoji=heart04><emoji=heart04><emoji=heart04>」"
    },
    {
        "name": "エンジュ",
        "message": "「呼啊，啊——嗯啊哈啊啊啊啊啊啊啊啊啊<emoji=heart04><emoji=heart04><emoji=heart04>」"
    },
    {
        "message": "紧紧塞满安洁阴道的肉棒激烈地搏动着，紧接着，以亿为单位的精子灌满了她的子宫。"
    },
    {
        "name": "エンジュ",
        "message": "「嗯啊<emoji=heart04> 哈，哈啊，啊啊……<emoji=heart04> 嗯啊，好厉害……能感觉到……<emoji=heart04> 肉棒，一抖一抖地……在肚子里跳动……<emoji=heart04>」"
    },
    {
        "name": "エンジュ",
        "message": "「咕咚，咕咚地，好多，好多呀<emoji=heart04> 魔王的精子，射出来了……在里面，咕噜咕噜地，射出来了……<emoji=heart04>」"
    },
    {
        "name": "クロト",
        "message": "「唔，安洁的小穴，夹得太紧了……！」"
    },
    {
        "name": "エンジュ",
        "message": "「还不是因为你那根大过头了……啊啊……舒，服死了……<emoji=heart04> 这世上竟然有这么舒服的事……<emoji=heart04>」"
    },
    {
        "message": "如此强烈的射精，我至今为止从未体验过。光是要保持意识清醒不晕过去，就已经竭尽全力了。大脑都快要失常了。"
    },
    {
        "name": "エンジュ",
        "message": "「嗯嗯……你是打算射多少啊……第一次就突然，想让我怀孕吗……？ 啊啊嗯……<emoji=heart04>」"
    },
    {
        "name": "エンジュ",
        "message": "「嗯……<emoji=heart04> 拔出来了……这么大的东西，刚刚还在我身体里，我到现在还是不敢相信……」"
    },
    {
        "message": "结束任务的阴茎从安洁的穴内滑了出来，张开的大穴滴落着白浊的粘液。"
    },
    {
        "name": "エンジュ",
        "message": "「哈啊啊……肚子里，好暖和……这就是魔王的温度啊……<emoji=heart04>」"
    },
    {
        "message": "即使高潮已经结束，安洁的眼神依旧像在做梦一般迷离，半张着的嘴唇也还未合拢。"
    },
    {
        "name": "クロト",
        "message": "「谢谢你，安洁……真是最棒的初体验了……」"
    },
    {
        "name": "エンジュ",
        "message": "「我也是……谢谢。没想到，和你会发展成这样的关系……刚认识的时候，想都不敢想呢」"
    },
    {
        "name": "エンジュ",
        "message": "「和别人肌肤相亲，居然是这么舒服的事……像这样互相触碰，感觉也不赖嘛……<emoji=heart04>」"
    },
    {
        "name": "エンジュ",
        "message": "「呐，魔王，抱紧我……」"
    },
    {
        "message": "我从背后用力抱紧了她那还有些发烫的身体。"
    },
    {
        "name": "エンジュ",
        "message": "「哈啊……哈啊，喜欢……最喜欢你了……<emoji=heart04> 以后，还会和我做爱吗……？」"
    },
    {
        "name": "クロト",
        "message": "「随时欢迎，乐意之至」"
    },
    {
        "name": "エンジュ",
        "message": "「好耶……哎嘿嘿嘿……<emoji=heart04>」"
    }
]