[
    {
        "name": "*S-ch10760018-1",
        "message": "「莫娜卡·阴道内射精版」"
    },
    {
        "name": "*S-ch10760018-2",
        "message": "「莫娜卡·阴道外射精版」"
    },
    {
        "name": "モナカ",
        "message": "「嘿，呀，哈——！」"
    },
    {
        "name": "クロト",
        "message": "「不错，就是这样！」"
    },
    {
        "name": "モナカ",
        "message": "「嗯。哥哥，再给我一根」"
    },
    {
        "message": "莫娜卡精神饱满的声音回荡在寂静的森林中。"
    },
    {
        "message": "不知从什么时候起，远离城镇的森林湖畔就成了我和莫娜卡的秘密特训场。"
    },
    {
        "name": "モナカ",
        "message": "「哈啊，哈啊，哎嘿嘿……一直以来都很谢谢你，哥哥。陪莫娜卡做训练……」"
    },
    {
        "name": "クロト",
        "message": "「我只是想和莫娜卡在一起而已。感觉就像在稍微约个会一样」"
    },
    {
        "name": "モナカ",
        "message": "「约——～～。好难为情啊……到现在，那个……我还是不敢相信，自己居然能和哥哥交往……」"
    },
    {
        "message": "看到莫娜卡羞得满脸通红，我的心跳不禁加速。"
    },
    {
        "message": "说实话……我真想立刻抱紧她。但是莫娜卡是个连牵手都会害羞的女孩子。"
    },
    {
        "message": "身为她的男朋友，我不想做太过性急的事，给莫娜卡添麻烦。"
    },
    {
        "name": "クロト",
        "message": "「好，好了，再比一场吧！」"
    },
    {
        "name": "モナカ",
        "message": "「嗯……！　要上了，哥哥……！」"
    },
    {
        "message": "为了驱散邪念，我决定和莫娜卡来一场小型比赛。"
    },
    {
        "message": "然而我刚跑起来就绊到了草丛──"
    },
    {
        "name": "モナカ",
        "message": "「呀！？」"
    },
    {
        "message": "我直接把莫娜卡压倒在了草丛上。"
    },
    {
        "message": "她的体温从我们交叠的身体上传了过来──"
    },
    {
        "name": "モナカ",
        "message": "「哥，哥哥大人……」"
    },
    {
        "name": "クロト",
        "message": "「唔。抱歉，我马上就让开……！」"
    },
    {
        "message": "我从未见过莫娜卡的脸离我这么近，于是急忙想要分开。"
    },
    {
        "name": "モナカ",
        "message": "「等，等等！　再稍微，哈啊哈啊，保持这样……」"
    },
    {
        "name": "クロト",
        "message": "「保持这样……」"
    },
    {
        "name": "モナカ",
        "message": "「因为……这是哥哥大人，第一次推倒我……」"
    },
    {
        "message": "莫娜卡没有整理好因为摔倒而弄乱的衣服，只是抬起眼睛注视着我。"
    },
    {
        "message": "莫娜卡汗湿的身体十分性感。"
    },
    {
        "message": "那小巧的胸部，以及比刚才还要红的脸，让我瞬间浑身发热。"
    },
    {
        "name": "モナカ",
        "message": "「可……可以摸摸我哦……？」"
    },
    {
        "name": "モナカ",
        "message": "「哥哥大人，您一直在忍耐着吧……对不对？　因为莫娜卡，那个，就连牵手都会慌得不得了……」"
    },
    {
        "name": "モナカ",
        "message": "「但是，那个……已经，没关系了……。不管哥哥大人对我做什么，莫娜卡都不会讨厌的……」"
    },
    {
        "name": "モナカ",
        "message": "「不，不是的……其实，那个，我一直……。一直都想让哥哥大人，对我做这种事情……」"
    },
    {
        "message": "莫娜卡一边说着，一边轻轻脱下了我的裤子。"
    },
    {
        "name": "モナカ",
        "message": "「诶，诶嘿嘿……终于帮您脱下来了……」"
    },
    {
        "name": "モナカ",
        "message": "「其实呀……？莫娜卡一直都很在意呢。因为每当莫娜卡靠近哥哥大人，那个……。哥哥大人的这里，就会不断变大……」"
    },
    {
        "name": "モナカ",
        "message": "「好想让哥哥大人……插进来哦？好想和哥哥大人合为一体……」"
    },
    {
        "name": "モナカ",
        "message": "「莫娜卡想正式成为哥哥大人的女朋友……。莫娜卡想和最喜欢的哥哥大人更加恩爱地亲热……」"
    },
    {
        "name": "モナカ",
        "message": "「哥哥大人，哈啊，哈啊……。可以和莫娜卡，做爱吗……？」"
    },
    {
        "message": "莫娜卡鼓起全部的勇气，向我提出了这个问题。"
    },
    {
        "message": "我当然不能不回应她的期待。"
    },
    {
        "name": "モナカ",
        "message": "「呼啊啊啊……！　啊，嗯唔……！　嗯啊嗯……！」"
    },
    {
        "message": "我一边撑开明显比我那根肉棒还要小还要窄的缝隙，一边尽可能缓慢地将阴茎插了进去。"
    },
    {
        "name": "モナカ",
        "message": "「哈啊，哈啊，哎嘿嘿……。终于和哥哥大人，嗯啊，合为一体了……」"
    },
    {
        "name": "モナカ",
        "message": "「莫娜卡能感觉到哦……？　哥哥大人正在进入莫娜卡的体内……」"
    },
    {
        "name": "モナカ",
        "message": "「好，啊啊嗯……。好暖和……。莫娜卡的阴道里，啊，哈啊……。一跳一跳的……」"
    },
    {
        "message": "莫娜卡像是在确认触感似的，紧紧……紧紧地……小心翼翼地搂住了我的阴茎。"
    },
    {
        "message": "她那拘谨的动作实在很有她的风格，让我深刻体会到了与莫娜卡合二为一的感觉。"
    },
    {
        "name": "モナカ",
        "message": "「啊……啊……啊啊嗯……。它还在不停地动着，哈啊啊嗯，好开心……」"
    },
    {
        "name": "モナカ",
        "message": "「如果是平时的哥哥大人，啊，哈啊……。一定会为了不让莫娜卡感到疼痛，而一动不动的……」"
    },
    {
        "name": "モナカ",
        "message": "「光是这样，诶嘿嘿……。哥哥大人也，兴奋起来了吗……？　和莫娜卡做爱，啊啊嗯，让你心跳不已吗……？」"
    },
    {
        "name": "モナカ",
        "message": "「在莫娜卡的里面抽插，呼啊……哈啊嗯……。有让你，舒服起来吗……？」"
    },
    {
        "message": "莫娜卡说得没错。明明我本来不打算刚插进去就马上动起来的，但却没法停下抽插。"
    },
    {
        "message": "莫娜卡娇喘着吐出甜蜜气息的模样，以及每插一下就会愈发湿润的秘部，都加速了我的兴奋和快感。"
    },
    {
        "name": "モナカ",
        "message": "「啊呼……啊……哈啊嗯……<emoji=heart04>　可，可以哦，哥哥大人……<emoji=heart04>　尽情地，啊啊嗯，用莫娜卡变得舒服吧……？」"
    },
    {
        "name": "モナカ",
        "message": "「莫娜卡也，啊……啊……<emoji=heart04>　很舒服，哦……<emoji=heart04>　哥哥大人硬硬的，啊啊嗯……<emoji=heart04>　在里面摩擦着……<emoji=heart04>」"
    },
    {
        "name": "モナカ",
        "message": "「虽然有点刺痛，啊，嗯……<emoji=heart04>　但比起那个，呼啊啊，更多的是，幸福和快感……<emoji=heart04>」"
    },
    {
        "name": "モナカ",
        "message": "「股间，呼啊，啊啊，变得湿哒哒的了……<emoji=heart04>　身体，哈啊哈啊，热得好像要融化了……<emoji=heart04>」"
    },
    {
        "message": "莫娜卡陶醉地眯起眼睛，因我的肉棒娇喘着，声音也变得更加娇艳。"
    },
    {
        "name": "モナカ",
        "message": "「再，啊，哈啊……<emoji=heart04>　插得更深一点，可以哦……<emoji=heart04>　不，莫娜卡想要哥哥大人插得更深一点……<emoji=heart04>」"
    },
    {
        "name": "モナカ",
        "message": "「我想感受……<emoji=heart04>　我想，更多地感受哥哥大人……<emoji=heart04>　其实我一直，哈啊哈啊，一直，都想和哥哥大人做色色的事情……<emoji=heart04>」"
    },
    {
        "message": "莫娜卡似乎也兴奋起来了，行为举止逐渐大胆起来。"
    },
    {
        "message": "她为了让我方便抽插而将双腿大大地分开，比刚才更加用力地缠紧肉棒。"
    },
    {
        "name": "モナカ",
        "message": "「莫娜卡，哈啊，哈啊，是个坏孩子……<emoji=heart04>　自从和哥哥大人开始交往之后，其实……啊，啊，脑子里就净是这些事情……<emoji=heart04>」"
    },
    {
        "name": "モナカ",
        "message": "「坐在哥哥大人腿上的时候也是，交往之前明明只是觉得很开心而已，哈啊，啊啊，交往之后，那个……<emoji=heart04>」"
    },
    {
        "name": "モナカ",
        "message": "「满脑子都是……满脑子都是哥哥大人的肉棒……<emoji=heart04>」"
    },
    {
        "name": "モナカ",
        "message": "「想着有朝一日能像这样，啊，啊，被哥哥大人的肉棒插入，和哥哥大人合为一体，坐在哥哥大人腿上把内裤都弄湿了……<emoji=heart04>」"
    },
    {
        "name": "モナカ",
        "message": "「对不起，呢……<emoji=heart04>　对不起，哥哥大人……<emoji=heart04>　哥哥大人明明一直在为了莫娜卡忍耐着……<emoji=heart04>」"
    },
    {
        "name": "モナカ",
        "message": "「莫娜卡……莫娜卡呢……<emoji=heart04>　坐在哥哥大人腿上，哈啊，哈啊，还会蹭来蹭去的……<emoji=heart04>」"
    },
    {
        "name": "モナカ",
        "message": "「在哥哥大人睡午觉的时候，哈啊，哈啊，还会偷偷亲上去……<emoji=heart04>」"
    },
    {
        "name": "モナカ",
        "message": "「回家之后，还会用哥哥大人握过的手，嗯啊，哈啊，用哥哥大人握过的手，自慰……<emoji=heart04>」"
    },
    {
        "name": "モナカ",
        "message": "「你会很瞧不起我吧……<emoji=heart04>　对不起，哈啊哈啊，真的很对不起，哥哥大人……<emoji=heart04>　我居然这么不像话……<emoji=heart04>」"
    },
    {
        "message": "或许是快感让她的大脑变得迷迷糊糊了，莫娜卡向我坦白了她的一切。"
    },
    {
        "message": "但是，如果要说这种话，那我──"
    },
    {
        "name": "モナカ",
        "message": "「咿啊<emoji=heart04>　啊，啊，啊，啊，啊<emoji=heart04><emoji=heart04>　为，什么<emoji=heart04>　哥哥大人，啊啊啊嗯，突然……<emoji=heart04><emoji=heart04><emoji=heart04>」"
    },
    {
        "name": "モナカ",
        "message": "「这么开心呢？莫娜卡明明，啊啊啊嗯，这么不像话，这么下流……<emoji=heart04>」"
    },
    {
        "message": "我没有点头，而是狠狠地把腰顶进了狭窄的小穴里。我一边顶着莫娜卡的子宫，一边把整根肉棒都插进了她的小穴里。"
    },
    {
        "message": "我也一直很想和莫娜卡做爱啊。就连她坐在我的腿上时，我勃起得裤子上都留下了湿痕。"
    },
    {
        "message": "我甚至每晚都在妄想和莫娜卡做爱──"
    },
    {
        "name": "モナカ",
        "message": "「啊，哈，嗯啊，啊啊嗯……<emoji=heart04>　哎嘿，哎嘿嘿，这样啊……<emoji=heart04>　原来哥哥大人和莫娜卡做着一样的事啊……<emoji=heart04>」"
    },
    {
        "name": "モナカ",
        "message": "「好开心哦，哥哥大人……<emoji=heart04>　莫娜卡真的好开心……<emoji=heart04>」"
    },
    {
        "name": "モナカ",
        "message": "「从今以后，啊，哈啊，我们还要，尽情地亲热哦……<emoji=heart04>」"
    },
    {
        "name": "モナカ",
        "message": "「莫娜卡，呼啊，啊啊，好想和哥哥大人尽情地亲热……<emoji=heart04>」"
    },
    {
        "name": "モナカ",
        "message": "「好想和哥哥大人接吻……<emoji=heart04>　好想让哥哥大人揉胸……<emoji=heart04>　好想让哥哥大人的肉棒，啊，啊，狠狠地插莫娜卡的小穴……<emoji=heart04>」"
    },
    {
        "message": "莫娜卡一边盯着我的脸看，一边紧紧地抱住我的肉棒。"
    },
    {
        "message": "她开心地抽动着身体，同时撅起嘴唇。"
    },
    {
        "name": "モナカ",
        "message": "「嗯啾……<emoji=heart04>　嗯呼，嗯，啾，啾噜……啾噜噜……<emoji=heart04>」"
    },
    {
        "name": "モナカ",
        "message": "「噗哈啊……啊啊嗯，啊，啊，啊，啊哈啊啊嗯……<emoji=heart04>」"
    },
    {
        "message": "我忍不住夺走莫娜卡的嘴唇，同时揉搓着她那软绵绵的小奶子，顺从着欲望索求着莫娜卡。"
    },
    {
        "name": "モナカ",
        "message": "「好幸福……<emoji=heart04>　哥哥大人，啊，哈啊，哥哥大人这么深爱着莫娜卡……<emoji=heart04>」"
    },
    {
        "name": "モナカ",
        "message": "「喜欢……<emoji=heart04>　好喜欢你，哥哥大人……<emoji=heart04>　最喜欢你了……<emoji=heart04>　喜欢……<emoji=heart04>」"
    },
    {
        "name": "モナカ",
        "message": "「脑子里，啊，啊，已经只剩下这个了……<emoji=heart04>　哥哥大人……<emoji=heart04>　啊啊啊嗯，哥哥大人……<emoji=heart04>」"
    },
    {
        "message": "我能感受到，不善言辞的莫娜卡正在竭尽全力地向我传达着她的心意。"
    },
    {
        "message": "从她湿漉漉的私处，从她火热的躯体，都能感受到莫娜卡此刻正欲火焚身，仿佛随时都会高潮一般。"
    },
    {
        "name": "モナカ",
        "message": "「啊，啊，啊，啊<emoji=heart04>　好舒服……<emoji=heart04>　哥哥大人的肉棒，在莫娜卡的阴道里变得越来越大……<emoji=heart04>」"
    },
    {
        "name": "モナカ",
        "message": "「哥哥大人，就在莫娜卡的里面……<emoji=heart04>　和最爱的，啊，啊，和最爱的哥哥大人，变得如此亲密……<emoji=heart04>」"
    },
    {
        "message": "这种幸福的一体感刺激着我的本能。"
    },
    {
        "message": "肉棒开始颤动，仿佛在与之呼应一般，莫娜卡的阴道也紧紧地收缩起来。──"
    },
    {
        "name": "モナカ",
        "message": "「啊呼啊<emoji=heart04>　好舒服<emoji=heart04>　好舒服啊，哥哥大人<emoji=heart04>」"
    },
    {
        "name": "モナカ",
        "message": "「被哥哥大人的肉棒狠狠抽插，真的好舒服……<emoji=heart04>　小穴的刺痛感，啊哈啊，逐渐变成了甜蜜的紧缩感……<emoji=heart04>」"
    },
    {
        "name": "モナカ",
        "message": "「好像要去了……<emoji=heart04>　要去了……<emoji=heart04>　好想和哥哥大人，呼啊啊啊，好想和哥哥大人一起高潮……<emoji=heart04>」"
    },
    {
        "name": "モナカ",
        "message": "「但是，啊呼啊啊，忍不住了……<emoji=heart04>　脑袋里晕乎乎的，小穴，也一紧一紧的……<emoji=heart04>」"
    },
    {
        "name": "モナカ",
        "message": "「不行了，嗯啊啊啊啊，要去了，去了，去了去了<emoji=heart04><emoji=heart04><emoji=heart04>」"
    },
    {
        "name": "モナカ",
        "message": "「对不起……<emoji=heart04>　连这种时候都这么没用，对不起……<emoji=heart04>　是个连高潮都忍不住的坏孩子，对不起……<emoji=heart04>」"
    },
    {
        "name": "モナカ",
        "message": "「但是太舒服了<emoji=heart04>　啊，啊，啊<emoji=heart04>　哥哥大人好舒服啊<emoji=heart04>」"
    },
    {
        "name": "モナカ",
        "message": "「不行了<emoji=heart04>　啊，啊啊啊<emoji=heart04>　忍不住了，啊啊啊啊，啊啊啊啊啊啊啊啊～～<emoji=heart04><emoji=heart04><emoji=heart04>」"
    },
    {
        "name": "モナカ",
        "message": "「对不起，对不起，对不起<emoji=heart04>　我是个好色的孩子，对不起～<emoji=heart04><emoji=heart04><emoji=heart04>」"
    },
    {
        "name": "モナカ",
        "message": "「呼啊——啊，哈啊啊啊啊啊啊啊啊嗯嗯嗯嗯嗯～～<emoji=heart04><emoji=heart04><emoji=heart04>」"
    },
    {
        "message": "在莫娜卡高潮的瞬间，我用力抱紧她的身体，将所有的精液注入她那小小的子宫中。"
    },
    {
        "name": "モナカ",
        "message": "「啊呼啊……<emoji=heart04>　啊啊啊啊……<emoji=heart04>　这个，哈呼啊……<emoji=heart04>　哥哥大人的……<emoji=heart04>　热热的东西，啊啊，好多……<emoji=heart04>」"
    },
    {
        "name": "モナカ",
        "message": "「诶嘿，诶嘿嘿……<emoji=heart04>　谢谢，哥哥大人……<emoji=heart04>　和莫娜卡，嗯啊啊啊嗯，和莫娜卡一起高潮了……<emoji=heart04>」"
    },
    {
        "name": "モナカ",
        "message": "「射了好多好多……<emoji=heart04>　哥哥大人的，啊啊嗯，射到莫娜卡的婴儿房里了……<emoji=heart04>」"
    },
    {
        "name": "モナカ",
        "message": "「真的好开心……<emoji=heart04>　哥哥大人在莫娜卡的体内……<emoji=heart04>　莫娜卡的身体，被哥哥大人填满了……<emoji=heart04>」"
    },
    {
        "name": "モナカ",
        "message": "「诶嘿，诶嘿嘿……<emoji=heart04>　好幸福……<emoji=heart04>　最喜欢哥哥大人了……<emoji=heart04>　喜欢……<emoji=heart04>　好想全部接受……<emoji=heart04>」"
    },
    {
        "message": "我才是幸福得不得了。莫娜卡开心地痉挛着，真是可爱得不得了。"
    },
    {
        "message": "光是看着她抬眼望着我的样子，我就随时都有可能射精。"
    },
    {
        "message": "在莫娜卡到达顶峰的瞬间，我将所有的精液射进了她娇小的身体里。"
    },
    {
        "name": "モナカ",
        "message": "「啊呼啊……<emoji=heart04>　啊啊啊啊……<emoji=heart04>　这个，哈呼啊……<emoji=heart04>　是哥哥大人……<emoji=heart04>　热热的，啊啊，好多好多……<emoji=heart04>」"
    },
    {
        "name": "モナカ",
        "message": "「诶嘿，诶嘿嘿……<emoji=heart04>　谢谢，哥哥大人……<emoji=heart04>　和莫娜卡，嗯啊啊啊嗯，和莫娜卡一起高潮了……<emoji=heart04>」"
    },
    {
        "name": "モナカ",
        "message": "「射了好多好多……<emoji=heart04>　哥哥大人的，啊啊嗯……<emoji=heart04>」"
    },
    {
        "name": "モナカ",
        "message": "「莫娜卡真的好高兴……<emoji=heart04>　莫娜卡的身体，被哥哥大人填满了……<emoji=heart04>」"
    },
    {
        "name": "モナカ",
        "message": "「诶嘿，诶嘿嘿……<emoji=heart04>　好幸福……<emoji=heart04>　最喜欢哥哥大人了……<emoji=heart04>　好喜欢……<emoji=heart04>　好想全部接下……<emoji=heart04>」"
    },
    {
        "message": "我才觉得幸福得不得了呢。因快感而浑身痉挛的莫娜卡，真是可爱得让人受不了。"
    },
    {
        "message": "光是看到她仰视着我，我就随时有可能射精了。"
    },
    {
        "name": "モナカ",
        "message": "「哈呼啊……<emoji=heart04>　哈啊……哈啊……<emoji=heart04>　诶，诶嘿嘿……<emoji=heart04>　还在射个不停……<emoji=heart04>」"
    },
    {
        "name": "モナカ",
        "message": "「哥哥大人，很舒服吗……<emoji=heart04>　莫娜卡这种人，也能让哥哥大人……<emoji=heart04>」"
    },
    {
        "name": "クロト",
        "message": "「正因为对象是莫娜卡，我才能这么舒服。不是其他人，正因为是莫娜卡，我才能如此舒服」"
    },
    {
        "name": "モナカ",
        "message": "「～～呜呜<emoji=heart04>　不，不行啦，哥哥大人……<emoji=heart04>　莫娜卡，是个好色的女孩子，光是听到这些话，就要去了啦……<emoji=heart04>」"
    },
    {
        "name": "モナカ",
        "message": "「但是，诶嘿嘿……<emoji=heart04>　好开心……<emoji=heart04>　感觉终于真正意义上成为了哥哥大人的恋人……<emoji=heart04>」"
    },
    {
        "message": "说着，莫娜卡双手环抱住我的后背，紧紧地抱住了我。"
    },
    {
        "name": "モナカ",
        "message": "「呐，哥哥大人……。莫娜卡还能再提一个任性的要求吗……？」"
    },
    {
        "name": "モナカ",
        "message": "「莫娜卡想就这样……。和哥哥大人连接在一起一会儿……不想和哥哥大人分开……。但是，要是会给哥哥大人添麻烦的话，那个……」"
    },
    {
        "name": "クロト",
        "message": "「怎么会添麻烦呢。我反倒还想和你继续亲热呢」"
    },
    {
        "name": "モナカ",
        "message": "「哥哥大人……哎嘿嘿。那就……来吧？　来亲热吧……？」"
    },
    {
        "name": "モナカ",
        "message": "「莫娜卡也想和哥哥大人更加更加地亲热……呐？」"
    },
    {
        "name": "モナカ",
        "message": "「啊，呼啊，哈啊啊啊啊……哈，哈啊，哎嘿嘿……嗯，嗯呼……哈啊，哈啊……呼……啊，嗯，哎嘿嘿……哈啊……啊啊……」"
    }
]